[
  {
    "id": "program-1755741619050",
    "programType": "CxO Events (1:Few)",
    "strategicPillars": "Pipeline Acceleration & Executive Engagement",
    "owner": "Shruti Narang",
    "quarter": "Q4 May",
    "fiscalYear": "FY26",
    "region": "South APAC",
    "country": "Vietnam",
    "forecastedCost": 100000,
    "expectedLeads": 1000,
    "revenuePlay": "New Business",
    "status": "On Track",
    "description": "TEST TEST TEST",
    "__modified": false,
    "__unsavedPriority": 0,
    "mqlForecast": 100,
    "pipelineForecast": 2400000
  },
  {
    "programType": "Localized Programs",
    "strategicPillars": "Account Growth and Product Adoption",
    "revenuePlay": "All",
    "fiscalYear": "FY26",
    "quarter": "Q1 - September",
    "region": "SAARC",
    "country": "India",
    "owner": "Shruti Narang",
    "description": "India",
    "forecastedCost": 10714,
    "expectedLeads": 250,
    "status": "Planning",
    "mqlForecast": 25,
    "pipelineForecast": 600000,
    "__unsavedPriority": 0,
    "__modified": false,
    "id": "row_1_1755741562563"
  },
  {
    "programType": "3P Sponsored Events",
    "strategicPillars": "New Logo Acquisition",
    "revenuePlay": "All",
    "fiscalYear": "FY26",
    "quarter": "Q1 - July",
    "region": "SAARC",
    "country": "India",
    "owner": "Shruti Narang",
    "description": "India",
    "forecastedCost": 10000,
    "expectedLeads": 250,
    "status": "Planning",
    "mqlForecast": 25,
    "pipelineForecast": 600000,
    "__unsavedPriority": 0,
    "__modified": false,
    "id": "row_2_1755741562563"
  },
  {
    "programType": "In-Account Events (1:1)",
    "strategicPillars": "Account Growth and Product Adoption",
    "revenuePlay": "All",
    "fiscalYear": "FY26",
    "quarter": "Q1 - August",
    "region": "SAARC",
    "country": "India",
    "owner": "Shruti Narang",
    "description": "India",
    "forecastedCost": 4000,
    "expectedLeads": 0,
    "status": "Planning",
    "mqlForecast": 0,
    "pipelineForecast": 80000,
    "__unsavedPriority": 0,
    "__modified": false,
    "id": "row_3_1755741562563"
  },
  {
    "programType": "In-Account Events (1:1)",
    "strategicPillars": "Account Growth and Product Adoption",
    "revenuePlay": "All",
    "fiscalYear": "FY26",
    "quarter": "Q1 - September",
    "region": "SAARC",
    "country": "India",
    "owner": "Shruti Narang",
    "description": "India",
    "forecastedCost": 4000,
    "expectedLeads": 0,
    "status": "Planning",
    "mqlForecast": 0,
    "pipelineForecast": 80000,
    "__unsavedPriority": 0,
    "__modified": false,
    "id": "row_4_1755741562563"
  },
  {
    "programType": "In-Account Events (1:1)",
    "strategicPillars": "Account Growth and Product Adoption",
    "revenuePlay": "All",
    "fiscalYear": "FY26",
    "quarter": "Q1 - July",
    "region": "SAARC",
    "country": "India",
    "owner": "Shruti Narang",
    "description": "India",
    "forecastedCost": 4000,
    "expectedLeads": 0,
    "status": "Planning",
    "mqlForecast": 0,
    "pipelineForecast": 80000,
    "__unsavedPriority": 0,
    "__modified": false,
    "id": "row_5_1755741562563"
  },
  {
    "programType": "In-Account Events (1:1)",
    "strategicPillars": "Account Growth and Product Adoption",
    "revenuePlay": "All",
    "fiscalYear": "FY26",
    "quarter": "Q1 - July",
    "region": "SAARC",
    "country": "India",
    "owner": "Shruti Narang",
    "description": "India",
    "forecastedCost": 4000,
    "expectedLeads": 0,
    "status": "Planning",
    "mqlForecast": 0,
    "pipelineForecast": 80000,
    "__unsavedPriority": 0,
    "__modified": false,
    "id": "row_7_1755741562563"
  },
  {
    "programType": "Localized Programs",
    "strategicPillars": "New Logo Acquisition",
    "revenuePlay": "All",
    "fiscalYear": "FY26",
    "quarter": "Q1 - August",
    "region": "SAARC",
    "country": "India",
    "owner": "Shruti Narang",
    "description": "India",
    "forecastedCost": 23810,
    "expectedLeads": 250,
    "status": "Planning",
    "mqlForecast": 25,
    "pipelineForecast": 600000,
    "__unsavedPriority": 0,
    "__modified": false,
    "id": "row_14_1755741562563"
  },
  {
    "programType": "Localized Programs",
    "strategicPillars": "New Logo Acquisition",
    "revenuePlay": "All",
    "fiscalYear": "FY26",
    "quarter": "Q1 - September",
    "region": "SAARC",
    "country": "India",
    "owner": "Shruti Narang",
    "description": "India",
    "forecastedCost": 15000,
    "expectedLeads": 200,
    "status": "Planning",
    "mqlForecast": 20,
    "pipelineForecast": 480000,
    "__unsavedPriority": 0,
    "__modified": false,
    "id": "row_15_1755741562563"
  },
  {
    "programType": "Operational/Infrastructure/Swag",
    "strategicPillars": "Brand Awareness & Top of Funnel Demand Generation",
    "fiscalYear": "FY26",
    "quarter": "Q1 - July",
    "region": "SAARC",
    "country": "India",
    "owner": "Shruti Narang",
    "description": "India",
    "forecastedCost": 20000,
    "expectedLeads": 0,
    "status": "Planning",
    "mqlForecast": 0,
    "pipelineForecast": 0,
    "__unsavedPriority": 0,
    "__modified": false,
    "id": "row_20_1755741562563"
  },
  {
    "programType": "In-Account Events (1:1)",
    "strategicPillars": "Account Growth and Product Adoption",
    "revenuePlay": "All",
    "fiscalYear": "FY26",
    "quarter": "Q2 - November",
    "region": "SAARC",
    "country": "India",
    "owner": "Shruti Narang",
    "description": "India",
    "forecastedCost": 4000,
    "expectedLeads": 0,
    "status": "Planning",
    "mqlForecast": 0,
    "pipelineForecast": 80000,
    "__unsavedPriority": 0,
    "__modified": false,
    "id": "row_6_1755741562563"
  },
  {
    "programType": "Lunch & Learns and Workshops (1:few)",
    "strategicPillars": "New Logo Acquisition",
    "revenuePlay": "All",
    "fiscalYear": "FY26",
    "quarter": "Q2 - November",
    "region": "SAARC",
    "country": "India",
    "owner": "Shruti Narang",
    "description": "India",
    "forecastedCost": 12048,
    "expectedLeads": 100,
    "status": "Planning",
    "mqlForecast": 10,
    "pipelineForecast": 240000,
    "__unsavedPriority": 0,
    "__modified": false,
    "id": "row_13_1755741562563"
  },
  {
    "programType": "Localized Programs",
    "strategicPillars": "Pipeline Acceleration & Executive Engagement",
    "revenuePlay": "All",
    "fiscalYear": "FY26",
    "quarter": "Q2 - November",
    "region": "SAARC",
    "country": "India",
    "owner": "Shruti Narang",
    "description": "India",
    "forecastedCost": 23810,
    "expectedLeads": 250,
    "status": "Planning",
    "mqlForecast": 25,
    "pipelineForecast": 600000,
    "__unsavedPriority": 0,
    "__modified": false,
    "id": "row_16_1755741562563"
  },
  {
    "programType": "Localized Programs",
    "strategicPillars": "Brand Awareness & Top of Funnel Demand Generation",
    "revenuePlay": "All",
    "fiscalYear": "FY26",
    "quarter": "Q2 - October",
    "region": "SAARC",
    "country": "Sri Lanka",
    "owner": "Shruti Narang",
    "description": "Sri Lanka",
    "forecastedCost": 25000,
    "expectedLeads": 200,
    "status": "Planning",
    "mqlForecast": 20,
    "pipelineForecast": 480000,
    "__unsavedPriority": 0,
    "__modified": false,
    "id": "row_17_1755741562563"
  },
  {
    "programType": "User Groups",
    "strategicPillars": "Account Growth and Product Adoption",
    "revenuePlay": "All",
    "fiscalYear": "FY26",
    "quarter": "Q2 - October",
    "region": "SAARC",
    "country": "India",
    "owner": "Shruti Narang",
    "description": "India",
    "forecastedCost": 15000,
    "expectedLeads": 100,
    "status": "Planning",
    "mqlForecast": 10,
    "pipelineForecast": 240000,
    "__unsavedPriority": 0,
    "__modified": false,
    "id": "row_18_1755741562563"
  },
  {
    "programType": "User Groups",
    "strategicPillars": "Pipeline Acceleration & Executive Engagement",
    "revenuePlay": "All",
    "fiscalYear": "FY26",
    "quarter": "Q2 - October",
    "region": "SAARC",
    "country": "India",
    "owner": "Shruti Narang",
    "description": "India",
    "forecastedCost": 15000,
    "expectedLeads": 100,
    "status": "Planning",
    "mqlForecast": 10,
    "pipelineForecast": 240000,
    "__unsavedPriority": 0,
    "__modified": false,
    "id": "row_19_1755741562563"
  },
  {
    "programType": "Localized Programs",
    "strategicPillars": "Account Growth and Product Adoption",
    "revenuePlay": "All",
    "fiscalYear": "FY26",
    "quarter": "Q2 - November",
    "region": "SAARC",
    "country": "India",
    "owner": "Shruti Narang",
    "description": "India",
    "forecastedCost": 15000,
    "expectedLeads": 250,
    "status": "Planning",
    "mqlForecast": 25,
    "pipelineForecast": 600000,
    "__unsavedPriority": 0,
    "__modified": false,
    "id": "row_21_1755741562563"
  },
  {
    "programType": "Localized Programs",
    "strategicPillars": "Account Growth and Product Adoption",
    "revenuePlay": "All",
    "fiscalYear": "FY26",
    "quarter": "Q2 - November",
    "region": "SAARC",
    "country": "India",
    "owner": "Shruti Narang",
    "description": "India",
    "forecastedCost": 10000,
    "expectedLeads": 300,
    "status": "Planning",
    "mqlForecast": 30,
    "pipelineForecast": 720000,
    "__unsavedPriority": 0,
    "__modified": false,
    "id": "row_23_1755741562563"
  },
  {
    "programType": "Flagship Events (Galaxy, Universe Recaps) 1:Many",
    "strategicPillars": "Account Growth and Product Adoption",
    "revenuePlay": "All",
    "fiscalYear": "FY26",
    "quarter": "Q2 - December",
    "region": "SAARC",
    "country": "India",
    "owner": "Shruti Narang",
    "description": "India",
    "forecastedCost": 10000,
    "expectedLeads": 300,
    "status": "Planning",
    "mqlForecast": 30,
    "pipelineForecast": 720000,
    "__unsavedPriority": 0,
    "__modified": false,
    "id": "row_24_1755741562563"
  },
  {
    "programType": "In-Account Events (1:1)",
    "strategicPillars": "Account Growth and Product Adoption",
    "revenuePlay": "All",
    "fiscalYear": "FY26",
    "quarter": "Q3 - January",
    "region": "SAARC",
    "country": "India",
    "owner": "Shruti Narang",
    "description": "India",
    "forecastedCost": 4000,
    "expectedLeads": 0,
    "status": "Planning",
    "mqlForecast": 0,
    "pipelineForecast": 80000,
    "__unsavedPriority": 0,
    "__modified": false,
    "id": "row_8_1755741562563"
  },
  {
    "programType": "In-Account Events (1:1)",
    "strategicPillars": "Account Growth and Product Adoption",
    "revenuePlay": "All",
    "fiscalYear": "FY26",
    "quarter": "Q3 - February",
    "region": "SAARC",
    "country": "India",
    "owner": "Shruti Narang",
    "description": "India",
    "forecastedCost": 4000,
    "expectedLeads": 0,
    "status": "Planning",
    "mqlForecast": 0,
    "pipelineForecast": 80000,
    "__unsavedPriority": 0,
    "__modified": false,
    "id": "row_9_1755741562563"
  },
  {
    "programType": "In-Account Events (1:1)",
    "strategicPillars": "Account Growth and Product Adoption",
    "revenuePlay": "All",
    "fiscalYear": "FY26",
    "quarter": "Q3 - March",
    "region": "SAARC",
    "country": "India",
    "owner": "Shruti Narang",
    "description": "India",
    "forecastedCost": 4000,
    "expectedLeads": 0,
    "status": "Planning",
    "mqlForecast": 0,
    "pipelineForecast": 80000,
    "__unsavedPriority": 0,
    "__modified": false,
    "id": "row_10_1755741562563"
  },
  {
    "programType": "In-Account Events (1:1)",
    "strategicPillars": "Account Growth and Product Adoption",
    "revenuePlay": "All",
    "fiscalYear": "FY26",
    "quarter": "Q3 - January",
    "region": "SAARC",
    "country": "India",
    "owner": "Shruti Narang",
    "description": "India",
    "forecastedCost": 4000,
    "expectedLeads": 0,
    "status": "Planning",
    "mqlForecast": 0,
    "pipelineForecast": 80000,
    "__unsavedPriority": 0,
    "__modified": false,
    "id": "row_11_1755741562563"
  },
  {
    "programType": "In-Account Events (1:1)",
    "strategicPillars": "Account Growth and Product Adoption",
    "revenuePlay": "All",
    "fiscalYear": "FY26",
    "quarter": "Q3 - February",
    "region": "SAARC",
    "country": "India",
    "owner": "Shruti Narang",
    "description": "India",
    "forecastedCost": 4000,
    "expectedLeads": 0,
    "status": "Planning",
    "mqlForecast": 0,
    "pipelineForecast": 80000,
    "__unsavedPriority": 0,
    "__modified": false,
    "id": "row_12_1755741562563"
  },
  {
    "programType": "Flagship Events (Galaxy, Universe Recaps) 1:Many",
    "strategicPillars": "Pipeline Acceleration & Executive Engagement",
    "revenuePlay": "All",
    "fiscalYear": "FY26",
    "quarter": "Q3 - January",
    "region": "SAARC",
    "country": "Sri Lanka",
    "owner": "Shruti Narang",
    "description": "Sri Lanka",
    "forecastedCost": 15000,
    "expectedLeads": 250,
    "status": "Planning",
    "mqlForecast": 25,
    "pipelineForecast": 600000,
    "__unsavedPriority": 0,
    "__modified": false,
    "id": "row_22_1755741562563"
  },
  {
    "programType": "Flagship Events (Galaxy, Universe Recaps) 1:Many",
    "strategicPillars": "Pipeline Acceleration & Executive Engagement",
    "revenuePlay": "All",
    "fiscalYear": "FY26",
    "quarter": "Q4 - May",
    "region": "SAARC",
    "country": "India",
    "owner": "Shruti Narang",
    "description": "India",
    "forecastedCost": 5000,
    "expectedLeads": 30,
    "status": "Planning",
    "mqlForecast": 3,
    "pipelineForecast": 72000,
    "__unsavedPriority": 0,
    "__modified": false,
    "id": "row_0_1755741562563"
  }
]